dbt_llm_tools/__init__.py
dbt_llm_tools/chatbot.py
dbt_llm_tools/dbt_model.py
dbt_llm_tools/dbt_project.py
dbt_llm_tools/documentation_generator.py
dbt_llm_tools/instructions.py
dbt_llm_tools/types.py
dbt_llm_tools/vector_store.py
dbt_llm_tools-0.2.0.dist-info/LICENSE.md
dbt_llm_tools-0.2.0.dist-info/METADATA
dbt_llm_tools-0.2.0.dist-info/WHEEL
dbt_llm_tools-0.2.0.dist-info/RECORD
