Metadata-Version: 2.1
Name: dbt-llm-tools
Version: 0.2.0
Summary: LLM based tools for dbt projects. Answer data questions, generate documentation and more.
Home-page: https://github.com/pragunbhutani/dbt-llm-tools
License: MIT
Keywords: dbt,openai,llm,data chatbot,dbt documentation
Author: Pragun Bhutani
Author-email: 1109752+pragunbhutani@users.noreply.github.com
Requires-Python: >=3.10,<4.0
Classifier: Development Status :: 2 - Pre-Alpha
Classifier: Intended Audience :: Developers
Classifier: License :: OSI Approved :: MIT License
Classifier: Operating System :: OS Independent
Classifier: Programming Language :: Python :: 3
Classifier: Programming Language :: Python :: 3.10
Classifier: Programming Language :: Python :: 3.11
Classifier: Programming Language :: Python :: 3.12
Classifier: Programming Language :: Python :: 3.13
Requires-Dist: PyYAML (>=6.0.1,<7.0.0)
Requires-Dist: chromadb (>=0.4.24,<0.5.0)
Requires-Dist: openai (>=1.16.0,<2.0.0)
Requires-Dist: streamlit (>=1.33.0,<2.0.0)
Requires-Dist: tinydb (>=4.8.0,<5.0.0)
Requires-Dist: typing-extensions (>=4.10.0,<5.0.0)
Project-URL: Repository, https://github.com/pragunbhutani/dbt-llm-tools
